fasttemplates/__init__.py
fasttemplates/constants.py
fasttemplates/main.py
fasttemplates/utils.py
fasttemplates/templates/baselayout/Dockerfile
fasttemplates/templates/baselayout/docker-compose.yml
fasttemplates/templates/baselayout/requirements.txt
fasttemplates/templates/baselayout/app/constants.py
fasttemplates/templates/baselayout/app/main.py
fasttemplates/templates/baselayout/app/settings.py
fasttemplates/templates/baselayout/app/routes/__init__.py
fasttemplates/templates/baselayout/app/routes/example.py
fasttemplates/templates/baselayout/app/utils/__init__.py
fasttemplates/templates/baselayout/app/utils/cache.py
fasttemplates/templates/baselayout/app/utils/logger.py
fasttemplates/templates/extras/cache/redis/app/utils/__init__.py
fasttemplates/templates/extras/cache/redis/app/utils/cache.py
fasttemplates/templates/extras/db/__init__.py
fasttemplates/templates/extras/db/mongo/__init__.py
fasttemplates/templates/extras/db/mongo/client.py
fasttemplates/templates/extras/db/redis/__init__.py
fasttemplates/templates/extras/db/redis/client.py
fast_templates-0.2.1.dist-info/LICENSE
fast_templates-0.2.1.dist-info/METADATA
fast_templates-0.2.1.dist-info/WHEEL
fast_templates-0.2.1.dist-info/entry_points.txt
fast_templates-0.2.1.dist-info/top_level.txt
fast_templates-0.2.1.dist-info/RECORD
