Metadata-Version: 2.1
Name: fast-templates
Version: 0.2.1
Summary: A CLI to generate FastAPI templates
Home-page: https://github.com/pybalt/FastAPI-TemplateWizard
Author: pybalt
Author-email: 96897286+pybalt@users.noreply.github.com
License-File: LICENSE
Requires-Dist: typer
Requires-Dist: questionary
Requires-Dist: pyyaml
